paramiko_gevent.py
setup.py
paramiko_gevent.egg-info/PKG-INFO
paramiko_gevent.egg-info/SOURCES.txt
paramiko_gevent.egg-info/dependency_links.txt
paramiko_gevent.egg-info/requires.txt
paramiko_gevent.egg-info/top_level.txt