Metadata-Version: 1.0
Name: paramiko-gevent
Version: 1.2
Summary: A tiny wrapper around Paramiko's SSHClient to enable running commands in parallel with gevent. 
Home-page: http://github.com/Fizzadar/paramiko-gevent
Author: Nick @ Oxygem
Author-email: nick@oxygem.com
License: UNKNOWN
Platform: UNKNOWN
